annotated_types/__init__.py
annotated_types/py.typed
annotated_types/test_cases.py
annotated_types-0.4.0.dist-info/METADATA
annotated_types-0.4.0.dist-info/WHEEL
annotated_types-0.4.0.dist-info/licenses/LICENSE
annotated_types-0.4.0.dist-info/RECORD
