Metadata-Version: 2.1
Name: annotated-types
Version: 0.4.0
Summary: Reusable constraint types to use with typing.Annotated
Author-email: Samuel Colvin <s@muelcolvin.com>, Adrian Garcia Badaracco <1755071+adriangb@users.noreply.github.com>, Zac Hatfield-Dodds <zac@zhd.dev>
License: The MIT License (MIT)
License-File: LICENSE
Classifier: Development Status :: 4 - Beta
Classifier: Environment :: Console
Classifier: Environment :: MacOS X
Classifier: Intended Audience :: Developers
Classifier: Intended Audience :: Information Technology
Classifier: License :: OSI Approved :: MIT License
Classifier: Operating System :: POSIX :: Linux
Classifier: Operating System :: Unix
Classifier: Programming Language :: Python :: 3 :: Only
Classifier: Programming Language :: Python :: 3.7
Classifier: Programming Language :: Python :: 3.8
Classifier: Programming Language :: Python :: 3.9
Classifier: Programming Language :: Python :: 3.10
Classifier: Programming Language :: Python :: 3.11
Classifier: Topic :: Software Development :: Libraries :: Python Modules
Classifier: Typing :: Typed
Requires-Python: >=3.7
Requires-Dist: typing-extensions>=4.0.0; python_version < '3.9'
